process_performance_indicators/__init__.py
process_performance_indicators/constants.py
process_performance_indicators/exceptions.py
process_performance_indicators/py.typed
process_performance_indicators/execution/__init__.py
process_performance_indicators/execution/_helpers.py
process_performance_indicators/execution/_registry.py
process_performance_indicators/execution/models.py
process_performance_indicators/execution/runner.py
process_performance_indicators/execution/summary.py
process_performance_indicators/formatting/__init__.py
process_performance_indicators/formatting/column_mapping.py
process_performance_indicators/formatting/conversions.py
process_performance_indicators/formatting/instance_id_generator.py
process_performance_indicators/formatting/log_formatter.py
process_performance_indicators/formatting/match.py
process_performance_indicators/indicators/__init__.py
process_performance_indicators/indicators/cost/__init__.py
process_performance_indicators/indicators/cost/activities.py
process_performance_indicators/indicators/cost/cases.py
process_performance_indicators/indicators/cost/groups.py
process_performance_indicators/indicators/cost/instances.py
process_performance_indicators/indicators/flexibility/__init__.py
process_performance_indicators/indicators/flexibility/activities.py
process_performance_indicators/indicators/flexibility/cases.py
process_performance_indicators/indicators/flexibility/groups.py
process_performance_indicators/indicators/general/__init__.py
process_performance_indicators/indicators/general/activities.py
process_performance_indicators/indicators/general/cases.py
process_performance_indicators/indicators/general/groups.py
process_performance_indicators/indicators/quality/__init__.py
process_performance_indicators/indicators/quality/activities.py
process_performance_indicators/indicators/quality/cases.py
process_performance_indicators/indicators/quality/groups.py
process_performance_indicators/indicators/quality/instances.py
process_performance_indicators-0.2.1.dist-info/METADATA
process_performance_indicators-0.2.1.dist-info/WHEEL
process_performance_indicators-0.2.1.dist-info/RECORD
