Metadata-Version: 2.4
Name: process-performance-indicators
Version: 0.2.1
Summary: A Python package for calculating process performance indicators
Requires-Python: >=3.10
Requires-Dist: pandas-stubs>=2.2.3.250308
Requires-Dist: pandas>=2.2.3
Requires-Dist: tqdm>=4.67.1
